cursbnr/__init__.py
cursbnr/bnr.py
cursbnr-0.1.1.dist-info/LICENSE
cursbnr-0.1.1.dist-info/METADATA
cursbnr-0.1.1.dist-info/WHEEL
cursbnr-0.1.1.dist-info/top_level.txt
cursbnr-0.1.1.dist-info/RECORD
